__init__.py
assets/icons/Arch-Category_Analytics_64.svg
assets/icons/Arch-Category_Application-Integration_64.svg
assets/icons/Arch-Category_Blockchain_64.svg
assets/icons/Arch-Category_Business-Applications_64.svg
assets/icons/Arch-Category_Cloud-Financial-Management_64.svg
assets/icons/Arch-Category_Compute_64.svg
assets/icons/Arch-Category_Contact-Center_64.svg
assets/icons/Arch-Category_Containers_64.svg
assets/icons/Arch-Category_Customer-Enablement_64.svg
assets/icons/Arch-Category_Database_64.svg
assets/icons/Arch-Category_Developer-Tools_64.svg
assets/icons/Arch-Category_End-User-Computing_64.svg
assets/icons/Arch-Category_Front-End-Web-Mobile_64.svg
assets/icons/Arch-Category_Games_64.svg
assets/icons/Arch-Category_Internet-of-Things_64.svg
assets/icons/Arch-Category_Machine-Learning_64.svg
assets/icons/Arch-Category_Management-Governance_64.svg
assets/icons/Arch-Category_Media-Services_64.svg
assets/icons/Arch-Category_Migration-Transfer_64.svg
assets/icons/Arch-Category_Networking-Content-Delivery_64.svg
assets/icons/Arch-Category_Quantum-Technologies_64.svg
assets/icons/Arch-Category_Robotics_64.svg
assets/icons/Arch-Category_Satellite_64.svg
assets/icons/Arch-Category_Security-Identity-Compliance_64.svg
assets/icons/Arch-Category_Serverless_64.svg
assets/icons/Arch-Category_Storage_64.svg
assets/icons/Arch_AWS-Activate_64.svg
assets/icons/Arch_AWS-Amplify_64.svg
assets/icons/Arch_AWS-App-Mesh_64.svg
assets/icons/Arch_AWS-App-Runner_64.svg
assets/icons/Arch_AWS-AppConfig_64.svg
assets/icons/Arch_AWS-AppFabric_64.svg
assets/icons/Arch_AWS-AppSync_64.svg
assets/icons/Arch_AWS-Application-Auto-Scaling_64.svg
assets/icons/Arch_AWS-Application-Composer_64.svg
assets/icons/Arch_AWS-Application-Cost-Profiler_64.svg
assets/icons/Arch_AWS-Application-Discovery-Service_64.svg
assets/icons/Arch_AWS-Application-Migration-Service_64.svg
assets/icons/Arch_AWS-Artifact_64.svg
assets/icons/Arch_AWS-Audit-Manager_64.svg
assets/icons/Arch_AWS-Auto-Scaling_64.svg
draws-1.0.0a3.dist-info/METADATA
draws-1.0.0a3.dist-info/WHEEL
draws-1.0.0a3.dist-info/top_level.txt
draws-1.0.0a3.dist-info/RECORD
